cml2tf-0.2.1.dist-info/METADATA
cml2tf-0.2.1.dist-info/WHEEL
cml2tf-0.2.1.dist-info/entry_points.txt
cml2tf-0.2.1.dist-info/licenses/LICENSE
cml2tf/__init__.py
cml2tf/main.py
cml2tf/templates/main.tf.j2
cml2tf/templates/variables.tf.j2
cml2tf/topology/CML2Topology.py
cml2tf/topology/__init__.py
cml2tf/topology/nodeconfig.py
cml2tf-0.2.1.dist-info/RECORD
