Metadata-Version: 2.1
Name: cml2tf
Version: 0.2.1
Summary: Convert CML2 lab topologies from YAML into HCL.
Author-Email: Piotr Wojciechowski <piotr@it-playground.pl>
License: MIT
Requires-Python: >=3.8
Requires-Dist: PyYAML>=6.0.1
Requires-Dist: argparse>=1.4.0
Requires-Dist: Jinja2>=3.1.3
